hvor/__init__.py
hvor/console.py
hvor/data.py
hvor/geolocator.py
hvor/hvor.py
hvor/resources/Fylker-2020-large.json.bz2
hvor/resources/Kommuner-2020-large.json.bz2
hvor-0.2.1.dist-info/entry_points.txt
hvor-0.2.1.dist-info/LICENSE
hvor-0.2.1.dist-info/WHEEL
hvor-0.2.1.dist-info/METADATA
hvor-0.2.1.dist-info/RECORD
