Metadata-Version: 2.1
Name: hvor
Version: 0.2.1
Summary: A library for assigning Norwegian metadata to coordinates
Home-page: https://github.com/bkkas/iout_foss
License: LGPL-3.0
Keywords: pandas,dataframe,geopandas
Author: Espen Hafstad Solvang, Erik Parmann, Kristian Flikka, Anna-Lena Both, Pål Grønås Drange
Requires-Python: >=3.8,<4.0
Classifier: License :: OSI Approved :: GNU Lesser General Public License v3 (LGPLv3)
Classifier: Programming Language :: Python :: 3
Classifier: Programming Language :: Python :: 3.8
Classifier: Programming Language :: Python :: 3.9
Requires-Dist: Rtree (>=0.9.7,<0.10.0)
Requires-Dist: geopandas (>=0.9.0,<0.10.0)
Requires-Dist: setuptools (>=57.4.0,<58.0.0)
Project-URL: Repository, https://github.com/bkkas/iout_foss
